osshared/__init__.py
osshared/auth/__init__.py
osshared/auth/auth.py
osshared/constant/__init__.py
osshared/constant/constant.py
osshared/constant/enum.py
osshared/constant/envConstant.py
osshared/entity/__init__.py
osshared/entity/entity.py
osshared/exception/__init__.py
osshared/exception/exception.py
osshared/exception/hooks.py
osshared/file/__init__.py
osshared/file/file.py
osshared/log/__init__.py
osshared/log/decorators.py
osshared/log/logger.py
osshared/middleware/requestLogging.py
osshared/request/__init__.py
osshared/request/enum.py
osshared/request/request.py
osshared/response/__init__.py
osshared/response/enum.py
osshared/response/response.py
osshared/response/responseBuilder.py
osshared-0.1.4.dist-info/METADATA
osshared-0.1.4.dist-info/WHEEL
osshared-0.1.4.dist-info/RECORD
