Metadata-Version: 2.3
Name: osShared
Version: 0.1.4
Summary: oasis version 2.0 shared python package
Author: Mr.Walter
Author-email: walter@vvnst.com
Requires-Python: >=3.11
Classifier: Programming Language :: Python :: 3
Classifier: Programming Language :: Python :: 3.11
Classifier: Programming Language :: Python :: 3.12
Classifier: Programming Language :: Python :: 3.13
Requires-Dist: djangorestframework (>=3.16.0,<4.0.0)
Requires-Dist: pydantic (>=2.0.0)
